dandelion/__init__.py
dandelion/external/README.md
dandelion/external/__init__.py
dandelion/external/anndata/_compat.py
dandelion/external/immcantation/__init__.py
dandelion/external/immcantation/changeo.py
dandelion/external/immcantation/scoper.py
dandelion/external/immcantation/shazam.py
dandelion/external/immcantation/tigger.py
dandelion/external/scanpy/__init__.py
dandelion/external/skbio/__init__.py
dandelion/external/skbio/_chao1.py
dandelion/external/skbio/_gini.py
dandelion/external/skbio/_shannon.py
dandelion/external/skbio/_utils.py
dandelion/logging/__init__.py
dandelion/logging/_badge.py
dandelion/logging/_logging.py
dandelion/logging/_metadata.py
dandelion/plotting/__init__.py
dandelion/plotting/_plotting.py
dandelion/preprocessing/__init__.py
dandelion/preprocessing/_preprocessing.py
dandelion/tools/__init__.py
dandelion/tools/_diversity.py
dandelion/tools/_network.py
dandelion/tools/_tools.py
dandelion/tools/_trajectory.py
dandelion/tools/calc_dist_matrix.py
dandelion/utilities/__init__.py
dandelion/utilities/_core.py
dandelion/utilities/_io.py
dandelion/utilities/_utilities.py
sc_dandelion-0.5.7.data/data/bin/MakeDb_gentle.py
sc_dandelion-0.5.7.data/data/bin/tigger-genotype.R
sc_dandelion-0.5.7.dist-info/licenses/LICENSE
sc_dandelion-0.5.7.dist-info/METADATA
sc_dandelion-0.5.7.dist-info/WHEEL
sc_dandelion-0.5.7.dist-info/top_level.txt
sc_dandelion-0.5.7.dist-info/RECORD
