Metadata-Version: 2.4
Name: sc-dandelion
Version: 0.5.7
Summary: sc-TCR/BCR-seq analysis tool
Author-email: zktuong <z.tuong@uq.edu.au>
License: GNU Affero General Public License v3 or later (AGPLv3+)
Project-URL: homepage, https://github.com/zktuong/dandelion/
Project-URL: documentation, https://sc-dandelion.readthedocs.io/
Keywords: dandelion,single-cell,immune,TCR,BCR
Classifier: Programming Language :: Python :: 3.11
Classifier: Programming Language :: Python :: 3.12
Classifier: Programming Language :: Python :: 3.13
Classifier: License :: OSI Approved :: GNU Affero General Public License v3 or later (AGPLv3+)
License-File: LICENSE
Requires-Dist: airr
Requires-Dist: setuptools_scm[toml]>=6.0
Requires-Dist: numpy>=1.23
Requires-Dist: pandas>=1.4
Requires-Dist: changeo>=1.1
Requires-Dist: anndata>=0.9
Requires-Dist: scanpy>=1.9
Requires-Dist: scikit-learn>=1.0
Requires-Dist: scipy>=1.8
Requires-Dist: numba>=0.56
Requires-Dist: seaborn>=0.12
Requires-Dist: networkx>=2.8
Requires-Dist: leidenalg>=0.9
Requires-Dist: polyleven>=0.4
Requires-Dist: h5py>=3.6
Requires-Dist: adjustText>=0.7
Requires-Dist: distance>=0.1.3
Requires-Dist: plotnine>=0.10
Requires-Dist: palettable>=3.3
Requires-Dist: mizani>=0.8
Requires-Dist: nxviz>=0.7
Provides-Extra: docs
Requires-Dist: airr; extra == "docs"
Requires-Dist: ipykernel; extra == "docs"
Requires-Dist: biopython>=1.79; extra == "docs"
Requires-Dist: changeo>=1; extra == "docs"
Requires-Dist: presto>=0.7; extra == "docs"
Requires-Dist: pyyaml>=5.4; extra == "docs"
Requires-Dist: yamlordereddictloader>=0.4; extra == "docs"
Requires-Dist: sphinx>=4.5; extra == "docs"
Requires-Dist: nbsphinx>=0.8; extra == "docs"
Requires-Dist: sphinx-autodoc-typehints>=1.18; extra == "docs"
Requires-Dist: sphinx_rtd_theme>=1.0; extra == "docs"
Requires-Dist: readthedocs-sphinx-ext>=2.1; extra == "docs"
Requires-Dist: recommonmark>=0.7; extra == "docs"
Provides-Extra: scirpy
Requires-Dist: scirpy>=0.21; extra == "scirpy"
Requires-Dist: awkward>=2.1; extra == "scirpy"
Requires-Dist: mudata>=0.2; extra == "scirpy"
Provides-Extra: scrublet
Requires-Dist: scrublet>=0.2; extra == "scrublet"
Requires-Dist: annoy<1.17.0; extra == "scrublet"
Provides-Extra: palantir
Requires-Dist: palantir>=0.2.3; extra == "palantir"
Requires-Dist: pertpy>=0.1.0; extra == "palantir"
Requires-Dist: jax>=0.3; extra == "palantir"
Dynamic: license-file
